peridot/__init__.py
peridot/__main__.py
peridot/version/catch.py
peridot/version/constants.py
peridot/version/context.py
peridot/version/default.py
peridot/version/exceptions.py
peridot/version/interpreter.py
peridot/version/lexer.py
peridot/version/modules/datetime.py
peridot/version/modules/file.py
peridot/version/modules/periscope.py
peridot/version/modules/sys.py
peridot/version/nodes.py
peridot/version/parser.py
peridot/version/repl.py
peridot/version/run.py
peridot/version/tokens.py
peridot/version/types.py
peridot-1.1.2.dist-info/entry_points.txt
peridot-1.1.2.dist-info/LICENSE.txt
peridot-1.1.2.dist-info/WHEEL
peridot-1.1.2.dist-info/METADATA
peridot-1.1.2.dist-info/RECORD
